{
  "id": 106050,
  "url": "https://www.spigotmc.org/resources/passaporto.106050/",
  "name": "Passaporto",
  "description": "Utile per i server roleplay per la possibilità di viaggiare",
  "authors": [
    "Alezino77"
  ],
  "numberOfDownloads": 32,
  "rating": 0,
  "numberOfVotes": 0,
  "releasesPageUrl": "https://www.spigotmc.org/resources/passaporto.106050/history",
  "releaseDate": 1667376540000,
  "updateDate": 1667376540000,
  "versions": [
    "1.16",
    "1.17",
    "1.18",
    "1.19"
  ]
}