{
  "id": 104905,
  "url": "https://www.spigotmc.org/resources/kitpvpwarpsn.104905/",
  "name": "KitPvPWarpsN",
  "description": "Warp FPS, LavaChallange and KnockBack 1.8",
  "authors": [
    "Nozem"
  ],
  "iconUrl": "https://www.spigotmc.org/data/resource_icons/104/104905.jpg?1661721065",
  "iconCid": "bafkreigwpvs3kdgygvauxdehbvruhemkcswjasfq6irfqiwxkj3vc3g7ai",
  "numberOfDownloads": 48,
  "rating": 5,
  "numberOfVotes": 1,
  "releasesPageUrl": "https://www.spigotmc.org/resources/kitpvpwarpsn.104905/history",
  "gitUrl": "https://github.com/NozemBR/KitPvPwarpsN/tree/master",
  "releaseDate": 1661717400000,
  "updateDate": 1661993880000,
  "versions": [
    "1.8"
  ]
}