{
  "id": 101161,
  "url": "https://www.spigotmc.org/resources/superpowers.101161/",
  "name": "Superpowers",
  "description": "Give players special abilities!",
  "authors": [
    "thymenaragon"
  ],
  "iconUrl": "https://www.spigotmc.org/data/resource_icons/101/101161.jpg?1649060562",
  "iconCid": "bafkreicfjtvxjh3qdxzv2wkr7roiv7mukjgf5kfqxsihg4taruqkh24sgm",
  "numberOfDownloads": 178,
  "rating": 0,
  "numberOfVotes": 0,
  "releasesPageUrl": "https://www.spigotmc.org/resources/superpowers.101161/history",
  "releaseDate": 1649056920000,
  "updateDate": 1649229720000,
  "versions": []
}