{
  "id": 99607,
  "url": "https://www.spigotmc.org/resources/fantastic-spawn.99607/",
  "name": "Fantastic Spawn",
  "description": "Fantastic spawn plugin!",
  "authors": [
    "iAmForyyDev_"
  ],
  "iconUrl": "https://www.spigotmc.org/data/resource_icons/99/99607.jpg?1645677066",
  "iconCid": "bafkreibkzeimxjthiyvk2h7zt6ohbre6nwwjeoeuwaskc5vw4yeodphfri",
  "numberOfDownloads": 76,
  "rating": 5,
  "numberOfVotes": 2,
  "releasesPageUrl": "https://www.spigotmc.org/resources/fantastic-spawn.99607/history",
  "gitUrl": "https://github.com/iAmForyy/FantasticSpawn",
  "releaseDate": 1643482500000,
  "updateDate": 1643686020000,
  "versions": [
    "1.8"
  ]
}