{
  "id": 696221,
  "url": "https://dev.bukkit.org/projects/restless",
  "name": "Restless",
  "description": "A plugin to control who can sleep",
  "archived": false,
  "authors": [
    "bradbot_1"
  ],
  "iconUrl": "https://media.forgecdn.net/avatars/630/683/638030234867385943.png",
  "iconCid": "bafkreibgj2rcnzwl33c73fgs5o6or5ro7jrl7pmyi4yuhjcdrickegmeo4",
  "numberOfDownloads": 40,
  "releasesPageUrl": "https://dev.bukkit.org/projects/restless/files",
  "gitUrl": "https://github.com/BradBot1/Restless",
  "releaseDate": 1667426686000,
  "updateDate": 1667428912000
}