{
  "id": 363141,
  "url": "https://dev.bukkit.org/projects/moneyonmobkill",
  "name": "MoneyOnMobKill",
  "description": "Get money on mob kill!",
  "archived": false,
  "authors": [
    "shivamCode"
  ],
  "iconUrl": "https://media.forgecdn.net/avatars/249/666/637174781616806293.png",
  "iconCid": "bafkreiemn5uf2ddvm4bn2h5rtgcpo25njiakaojdpfmdpcsjrxjm3gfscq",
  "numberOfDownloads": 1,
  "releasesPageUrl": "https://dev.bukkit.org/projects/moneyonmobkill/files",
  "releaseDate": 1581881361000,
  "updateDate": 1581881435000
}