{
  "id": 105127,
  "url": "https://www.spigotmc.org/resources/linkaccount.105127/",
  "name": "Linkaccount",
  "description": "linkaccount, web, getcode",
  "authors": [
    "vitekvitkov"
  ],
  "iconUrl": "https://www.spigotmc.org/data/resource_icons/105/105127.jpg?1662554199",
  "iconCid": "bafkreihj2ni4dkxzrv2ottllzrkym5viwre76cfv6nxk2ymxie3yj62shm",
  "numberOfDownloads": 18,
  "rating": 0,
  "numberOfVotes": 0,
  "releasesPageUrl": "https://www.spigotmc.org/resources/linkaccount.105127/history",
  "releaseDate": 1662550500000,
  "updateDate": 1662550500000,
  "versions": [
    "1.19"
  ]
}