{
  "id": 101689,
  "url": "https://www.spigotmc.org/resources/anti-color.101689/",
  "name": "Anti color",
  "description": "A minecraft manhunt plugin to block your from touching your color.",
  "authors": [
    "Eco-Error"
  ],
  "iconUrl": "https://www.spigotmc.org/data/resource_icons/101/101689.jpg?1651080664",
  "iconCid": "bafkreigwgup3qmumgjqnrvtrbav6qiflmlzqbolemutbtazgmpcunuukpa",
  "numberOfDownloads": 12,
  "rating": 0,
  "numberOfVotes": 0,
  "releasesPageUrl": "https://www.spigotmc.org/resources/anti-color.101689/history",
  "releaseDate": 1651077000000,
  "updateDate": 1651077000000,
  "versions": []
}