{
  "id": 103558,
  "url": "https://www.spigotmc.org/resources/custom-blood-pact-split-drops-by-damage-dealt.103558/",
  "name": "[Custom] Blood Pact | Split drops by damage dealt!",
  "description": "Mind if I roll bleed?",
  "authors": [
    "Overqualified"
  ],
  "iconUrl": "https://www.spigotmc.org/data/resource_icons/103/103558.jpg?1658410656",
  "iconCid": "bafkreici546hegs5m5k6jv3gwkvhufmpeytqmre6x5o5tvaetnz7hn5jfq",
  "numberOfDownloads": 28,
  "rating": 5,
  "numberOfVotes": 1,
  "releasesPageUrl": "https://www.spigotmc.org/resources/custom-blood-pact-split-drops-by-damage-dealt.103558/history",
  "releaseDate": 1658407020000,
  "updateDate": 1658407020000,
  "versions": [
    "1.13",
    "1.14",
    "1.15",
    "1.16",
    "1.17",
    "1.18",
    "1.19"
  ]
}