{
  "id": 314042,
  "url": "https://dev.bukkit.org/projects/joincommands-p",
  "name": "JoinCommands P",
  "description": "Add join commands to your server!",
  "archived": false,
  "authors": [
    "paperboypaddy16"
  ],
  "iconUrl": "https://media.forgecdn.net/avatars/190/454/636855914059201365.png",
  "iconCid": "bafkreihdubamm2dmmvlmutd5qyzknmn5pihmnd4o22qh5dqnoljfv7sivu",
  "numberOfDownloads": 376,
  "releasesPageUrl": "https://dev.bukkit.org/projects/joincommands-p/files",
  "releaseDate": 1549994605000,
  "updateDate": 1549994672000
}