{
  "id": 106801,
  "url": "https://www.spigotmc.org/resources/catsk.106801/",
  "name": "CatSK",
  "description": "An alternative for Essentials, yuck.",
  "authors": [
    "An0nymouse"
  ],
  "iconUrl": "https://www.spigotmc.org/data/resource_icons/106/106801.jpg?1671335539",
  "iconCid": "bafkreig7ndwwqvybq7d4r2rksl4zl647xp2fvzx72kye7efqndjqixopx4",
  "numberOfDownloads": 25,
  "rating": 0,
  "numberOfVotes": 0,
  "releasesPageUrl": "https://www.spigotmc.org/resources/catsk.106801/history",
  "releaseDate": 1671331860000,
  "updateDate": 1671333600000,
  "versions": [
    "1.17",
    "1.18",
    "1.19"
  ]
}