{
  "id": 614312,
  "url": "https://dev.bukkit.org/projects/myjoinleavemessage",
  "name": "MyJoinLeaveMessage",
  "description": "A simple plugin of custom enter and exit messages",
  "archived": false,
  "authors": [
    "Tech7"
  ],
  "iconUrl": "https://media.forgecdn.net/avatars/535/913/637857258767844227.png",
  "iconCid": "bafkreifhmtanrceefcyyonm2y7mnhq6knoracsq3qsphtl3hise2wpcc4a",
  "numberOfDownloads": 184,
  "releasesPageUrl": "https://dev.bukkit.org/projects/myjoinleavemessage/files",
  "releaseDate": 1650129076000,
  "updateDate": 1669902893000
}