{
  "id": 548263,
  "url": "https://dev.bukkit.org/projects/simplebckupplugin",
  "name": "SimpleBackupPlugin",
  "description": "Automatically  create backup folders for worlds ",
  "archived": true,
  "authors": [
    "Samhhcg"
  ],
  "iconUrl": "https://media.forgecdn.net/avatars/457/91/637729088521816030.png",
  "iconCid": "bafybeid4zp4iiv2vmfkm6frme4mmq3ph5slblfy4v246jj4q2xju6zq3ry",
  "numberOfDownloads": 423,
  "releasesPageUrl": "https://dev.bukkit.org/projects/simplebckupplugin/files",
  "releaseDate": 1637312052000,
  "updateDate": 1639498256000
}