{
  "name": "1.0.6-3",
  "version": {
    "name": "1.0.6.3",
    "downloadUrl": "resources/rd-locklogin-the-best-authentication-plugin-%E2%9C%85-fast%E2%9A%A1-reliable%E2%AD%90-secure%E2%AD%95.75156/download?version=385900",
    "numberOfDownloads": 90,
    "rating": 0,
    "numberOfVotes": 0,
    "releaseDate": 1614451500,
    "sourceUrl": "https://www.spigotmc.org/resources/rd-locklogin-the-best-authentication-plugin-%E2%9C%85-fast%E2%9A%A1-reliable%E2%AD%90-secure%E2%AD%95.75156/history"
  }
}