{
  "id": 87755,
  "url": "https://dev.bukkit.org/projects/spawnsystem",
  "name": "Spawnx",
  "description": "A spawn plugin which allows you to set spawns and go there! And you also have a Random Spawn system!",
  "archived": false,
  "authors": [
    "Xtomyserrax"
  ],
  "iconUrl": "https://media.forgecdn.net/avatars/84/412/636194859183569826.png",
  "iconCid": "bafkreifhcnmd4cikcrf2ppq5lqy6hinxnw4nk5eqalgo4fswpq7ilenydq",
  "numberOfDownloads": 12,
  "releasesPageUrl": "https://dev.bukkit.org/projects/spawnsystem/files",
  "releaseDate": 1418528217000,
  "updateDate": 1597467874000
}