{
  "id": 371665,
  "url": "https://dev.bukkit.org/projects/essentials-afk-room",
  "name": "Essentials AFK Room",
  "description": "Hooks into Essentials, will teleport AFK players to a certain location.",
  "archived": false,
  "authors": [
    "DerockGamer"
  ],
  "iconUrl": "https://media.forgecdn.net/avatars/259/116/637210352646392196.png",
  "iconCid": "bafybeic6ncbj2h5ojafp4c2wveyv3flkm2lzc26ykmm7225pmthn2jakvu",
  "numberOfDownloads": 577,
  "releasesPageUrl": "https://dev.bukkit.org/projects/essentials-afk-room/files",
  "releaseDate": 1585438464000,
  "updateDate": 1585438521000
}