{
  "id": 102515,
  "url": "https://www.spigotmc.org/resources/maesiamob-cr%C3%A9e-%C3%A9dit-les-mobs-en-jeu-directement.102515/",
  "name": "MaesiaMob Crée, édit les mobs en jeu directement",
  "description": "Crée, éditer les entités comme bon te semblant !",
  "authors": [
    "novah"
  ],
  "iconUrl": "https://www.spigotmc.org/data/resource_icons/102/102515.jpg?1654804328",
  "iconCid": "bafkreib3bb6qhhcrxtqtk3egl46qsmnufsqqftf3547vcxsr3j3tsvmgre",
  "numberOfDownloads": 21,
  "rating": 0,
  "numberOfVotes": 0,
  "releasesPageUrl": "https://www.spigotmc.org/resources/maesiamob-cr%C3%A9e-%C3%A9dit-les-mobs-en-jeu-directement.102515/history",
  "releaseDate": 1654798020000,
  "updateDate": 1654798020000,
  "versions": [
    "1.18"
  ]
}