{
  "id": 614580,
  "url": "https://dev.bukkit.org/projects/api-redispluginmessages-easier-plugin-messaging",
  "name": "API ⏩ RedisPluginMessages ✅ Easier Plugin Messaging between Servers! ⭕ Simple Messaging System",
  "description": "Spigot/BungeeCord plugin for PluginMessaging without a player using Redis, an in-memory database.",
  "archived": false,
  "authors": [
    "amata1219"
  ],
  "iconUrl": "https://media.forgecdn.net/avatars/536/231/637857971555228715.jpeg",
  "iconCid": "bafkreie3b72aus7hhtkhskifgstvollrzbooaqhsbcx73ptip6d5sb3qoi",
  "numberOfDownloads": 64,
  "releasesPageUrl": "https://dev.bukkit.org/projects/api-redispluginmessages-easier-plugin-messaging/files",
  "releaseDate": 1650200355000,
  "updateDate": 1650200402000
}