{
  "id": 105648,
  "url": "https://www.spigotmc.org/resources/1-12-2-%E2%AD%90rpidentity%E2%AD%90-%E2%9C%A8-1-roleplay-identity-card-plugin-%E2%9C%85placeholderapi-support.105648/",
  "name": "1.12.2 ⭐RPIdentity⭐|✨#1 RolePlay Identity Card Plugin|✅PlaceholderAPI Support!",
  "description": "RolePlay Identity Card Plugin",
  "authors": [
    "federclslf"
  ],
  "iconUrl": "https://www.spigotmc.org/data/resource_icons/105/105648.jpg?1665073925",
  "iconCid": "bafkreigxlaboiuxfqpm5ryvddkr2qogikf2pjzzeljjuhzagrxjvzxvrla",
  "numberOfDownloads": 181,
  "rating": 0,
  "numberOfVotes": 0,
  "releasesPageUrl": "https://www.spigotmc.org/resources/1-12-2-%E2%AD%90rpidentity%E2%AD%90-%E2%9C%A8-1-roleplay-identity-card-plugin-%E2%9C%85placeholderapi-support.105648/history",
  "releaseDate": 1665070260000,
  "updateDate": 1665330720000,
  "versions": [
    "1.12"
  ]
}