{
  "id": 103579,
  "url": "https://www.spigotmc.org/resources/betterexplosions.103579/",
  "name": "BetterExplosions",
  "description": "Plugin that makes explosions look cooler",
  "authors": [
    "barbosaur"
  ],
  "iconUrl": "https://www.spigotmc.org/data/resource_icons/103/103579.jpg?1672646826",
  "iconCid": "bafkreicbxikbg77v2t2vika4tg6rmar3hpz3ajsm6vfv5onbt6s6gi5sf4",
  "numberOfDownloads": 46,
  "rating": 5,
  "numberOfVotes": 1,
  "releasesPageUrl": "https://www.spigotmc.org/resources/betterexplosions.103579/history",
  "releaseDate": 1658464980000,
  "updateDate": 1658464980000,
  "versions": [
    "1.19"
  ]
}