{
  "id": 689084,
  "url": "https://dev.bukkit.org/projects/specialarrows",
  "name": "Specialarrows",
  "description": "Add new arrows to your minecraft server",
  "archived": false,
  "authors": [
    "TheDutchRuben"
  ],
  "iconUrl": "https://media.forgecdn.net/avatars/622/524/638015212290134999.png",
  "iconCid": "bafkreigchit57ycx5abpbliwrcq6357z6xaboyzhyz6zmojazof3gllmlq",
  "numberOfDownloads": 63,
  "releasesPageUrl": "https://dev.bukkit.org/projects/specialarrows/files",
  "releaseDate": 1665924428000,
  "updateDate": 1665924548000
}