{
  "id": 422939,
  "url": "https://dev.bukkit.org/projects/enderchest-invsee-craft-see",
  "name": "EnderChest, EnderChestSee, InvSee, Craft",
  "description": "A Plugin with that you can use the command /ec to open your EnderChest and /craft to open a CraftingTable. As an Operator, you can also open the Invento...",
  "archived": false,
  "authors": [
    "Forge_User_23779241"
  ],
  "iconUrl": "https://media.forgecdn.net/avatars/317/81/637420678238175686.png",
  "iconCid": "bafkreiebi44p35vi3eqq53vkebivcqnrbe4hrwwgppwta2ow4wlgz73vr4",
  "numberOfDownloads": 10,
  "releasesPageUrl": "https://dev.bukkit.org/projects/enderchest-invsee-craft-see/files",
  "releaseDate": 1606471023000,
  "updateDate": 1606471069000
}