{
  "id": 846980,
  "url": "https://dev.bukkit.org/projects/litespectator",
  "name": "LiteSpectator",
  "description": "Spectate game on command and be reset to previous position when going back to survival.",
  "archived": false,
  "authors": [
    "jonnyfant"
  ],
  "iconUrl": "https://media.forgecdn.net/avatars/800/460/638163791817348207.jpeg",
  "iconCid": "bafkreiasrxuqxkpz7g5mwwml33rdq66xxkuzus5whq5i57moekyj7jxhka",
  "numberOfDownloads": 32,
  "releasesPageUrl": "https://dev.bukkit.org/projects/litespectator/files",
  "gitUrl": "https://github.com/JonathanHoffmann/BukkitLiteSpectator",
  "releaseDate": 1680782381000,
  "updateDate": 1680782473000
}