{
  "id": 372618,
  "url": "https://dev.bukkit.org/projects/flowermap",
  "name": "FlowerMap",
  "description": "Displays a textual map of bonemeal flower generation in Flower Forests",
  "archived": false,
  "authors": [
    "CraigParton"
  ],
  "iconUrl": "https://media.forgecdn.net/avatars/260/210/637213795939139078.jpeg",
  "iconCid": "bafkreidma3o6tgplz343mrdeds3dqxtdoczie2m3wszds2inec3lwdhlvu",
  "numberOfDownloads": 108,
  "releasesPageUrl": "https://dev.bukkit.org/projects/flowermap/files",
  "gitUrl": "https://github.com/CraigParton/FlowerMap",
  "releaseDate": 1585782793000,
  "updateDate": 1585784756000
}