{
  "id": 93741,
  "url": "https://www.spigotmc.org/resources/lavatrash-pocket-trash-can.93741/",
  "name": "LavaTrash - Pocket trash can",
  "description": "Easily delete your items from your inventory!",
  "authors": [
    "RedBoard"
  ],
  "iconUrl": "https://www.spigotmc.org/data/resource_icons/93/93741.jpg?1624996162",
  "iconCid": "bafkreihqxoh5llt4pbtf4sj24i7oywbnxhncan7flfydcb622eumklgiyq",
  "numberOfDownloads": 140,
  "rating": 5,
  "numberOfVotes": 2,
  "releasesPageUrl": "https://www.spigotmc.org/resources/lavatrash-pocket-trash-can.93741/history",
  "releaseDate": 1624991880000,
  "updateDate": 1645281480000,
  "versions": [
    "1.7",
    "1.8",
    "1.9",
    "1.10",
    "1.11",
    "1.12",
    "1.13",
    "1.14",
    "1.15",
    "1.16",
    "1.17"
  ]
}