{
  "id": 479056,
  "url": "https://dev.bukkit.org/projects/mi",
  "name": "MI",
  "description": "A plugin that allows the creation of custom items.",
  "archived": false,
  "authors": [
    "samodoom1"
  ],
  "iconUrl": "https://media.forgecdn.net/avatars/378/675/637558123889972821.jpeg",
  "iconCid": "bafkreicvg3dz7gqxh5uvn5lwqk4a5m5xcuwkiknlstlfqmcfhdyghaxlqi",
  "numberOfDownloads": 127,
  "releasesPageUrl": "https://dev.bukkit.org/projects/mi/files",
  "releaseDate": 1620215588000,
  "updateDate": 1620215637000
}