{
  "id": 304992,
  "url": "https://dev.bukkit.org/projects/kfg_ranks",
  "name": "KFG_Ranks",
  "description": "plugin ranks from Dev KingFor",
  "archived": false,
  "authors": [
    "kingfor_decv"
  ],
  "iconUrl": "https://media.forgecdn.net/avatars/174/731/636753073030787048.jpeg",
  "iconCid": "bafkreifsmdjqvxx5g6zjmejjydoo4unkhlyvoelyeb6b2hqlmqprzi66xa",
  "numberOfDownloads": 925,
  "releasesPageUrl": "https://dev.bukkit.org/projects/kfg_ranks/files",
  "releaseDate": 1539710503000,
  "updateDate": 1539710913000
}