{
  "id": 339583,
  "url": "https://dev.bukkit.org/projects/superchatclear",
  "name": "Server Chat Control - SuperChatClear",
  "description": "Chat Control",
  "archived": false,
  "authors": [
    "spacebytee"
  ],
  "iconUrl": "https://media.forgecdn.net/avatars/223/418/637029103808904727.png",
  "iconCid": "bafkreiaf3kn52bu5xi5m627ictbec72embj3v5c5rejldktmieaq2buowa",
  "numberOfDownloads": 182,
  "releasesPageUrl": "https://dev.bukkit.org/projects/superchatclear/files",
  "releaseDate": 1567313580000,
  "updateDate": 1567313678000
}