{
  "id": 107005,
  "url": "https://www.spigotmc.org/resources/starstaff-beta.107005/",
  "name": "StarStaff (Beta)",
  "description": "A Staff Plugin Where You Can, Go Invisible, Broadcast Messages, etc.",
  "authors": [
    "DiscoTheOfficial"
  ],
  "numberOfDownloads": 37,
  "rating": 0,
  "numberOfVotes": 0,
  "releasesPageUrl": "https://www.spigotmc.org/resources/starstaff-beta.107005/history",
  "releaseDate": 1672165140000,
  "updateDate": 1672220280000,
  "versions": [
    "1.17",
    "1.18",
    "1.19"
  ]
}