{
  "id": 96692,
  "url": "https://www.spigotmc.org/resources/inventorypunch.96692/",
  "name": "InventoryPunch",
  "description": "Open players inventory/enderchest with a punch! <or commands>",
  "authors": [
    "MrCreeper1216"
  ],
  "iconUrl": "https://www.spigotmc.org/data/resource_icons/96/96692.jpg?1633627888",
  "iconCid": "bafkreidmdufbwulgnu5cvoqkhteua2u7i7ifcuuq73pn5w4x4phlin7wi4",
  "numberOfDownloads": 60,
  "rating": 5,
  "numberOfVotes": 1,
  "releasesPageUrl": "https://www.spigotmc.org/resources/inventorypunch.96692/history",
  "releaseDate": 1633624260000,
  "updateDate": 1655650440000,
  "versions": [
    "1.8",
    "1.9",
    "1.10",
    "1.11",
    "1.12",
    "1.13",
    "1.14",
    "1.15",
    "1.16",
    "1.17",
    "1.18",
    "1.19"
  ]
}