{
  "id": 319160,
  "url": "https://dev.bukkit.org/projects/project-pizzaplugin",
  "name": "Project PizzaPlugin",
  "description": "A plugin for beginning owners!",
  "archived": false,
  "authors": [
    "TheGamerAdmin"
  ],
  "iconUrl": "https://media.forgecdn.net/avatars/199/129/636904449077867287.png",
  "iconCid": "bafkreifaidlqmzefofcp3tkrdpzr4hfifxyjxre6tmlc5rso5jz6ca44ye",
  "numberOfDownloads": 184,
  "releasesPageUrl": "https://dev.bukkit.org/projects/project-pizzaplugin/files",
  "releaseDate": 1554847199000,
  "updateDate": 1554903097000
}