{
  "id": 275381,
  "url": "https://dev.bukkit.org/projects/bukkit-explosion-physics-works-with-modded",
  "name": "Structure Physics",
  "description": "Do you want caves to collapse in on itself if it explodes? do you want walls to crumble from a tank shell? well, this is the plugin for you!",
  "archived": false,
  "authors": [
    "unity5development"
  ],
  "iconUrl": "https://media.forgecdn.net/avatars/112/560/636392507314987538.png",
  "iconCid": "bafkreighqghosgit644r2fyzlhrgkworortsdvpixk5s35s4rdewzda6mi",
  "numberOfDownloads": 198,
  "releasesPageUrl": "https://dev.bukkit.org/projects/bukkit-explosion-physics-works-with-modded/files",
  "gitUrl": "https://github.com/rater193/StructurePhysics",
  "releaseDate": 1503671931000,
  "updateDate": 1503727765000
}