{
  "id": 69339,
  "url": "https://www.spigotmc.org/resources/minimalist-no-enderpearl-endermites.69339/",
  "name": "[Minimalist] No Enderpearl Endermites",
  "description": "Prevents Endermites from spawning after Enderpearl Teleports",
  "authors": [
    "c-eAgle"
  ],
  "numberOfDownloads": 280,
  "rating": 3.7,
  "numberOfVotes": 3,
  "releasesPageUrl": "https://www.spigotmc.org/resources/minimalist-no-enderpearl-endermites.69339/history",
  "releaseDate": 1563123540000,
  "updateDate": 1658753940000,
  "versions": [
    "1.15",
    "1.16",
    "1.17",
    "1.18",
    "1.19"
  ]
}