{
  "id": 105094,
  "url": "https://www.spigotmc.org/resources/hardcoreplus.105094/",
  "name": "HardcorePlus",
  "description": "each player has three lives, temp-banned on last death",
  "authors": [
    "lilsimmi"
  ],
  "iconUrl": "https://www.spigotmc.org/data/resource_icons/105/105094.jpg?1667483125",
  "iconCid": "bafkreiaq6eqleansp3fgofww2lv7ovrf5gyd7r3dsfsel3fg74i5gokpze",
  "numberOfDownloads": 135,
  "rating": 0,
  "numberOfVotes": 0,
  "releasesPageUrl": "https://www.spigotmc.org/resources/hardcoreplus.105094/history",
  "releaseDate": 1662393000000,
  "updateDate": 1668002640000,
  "versions": [
    "1.18",
    "1.19"
  ]
}