{
  "id": 272926,
  "url": "https://dev.bukkit.org/projects/consolecmd",
  "name": "ConsoleCMD",
  "description": "Limit commands to console only!",
  "archived": false,
  "authors": [
    "_ForgeUser20150265"
  ],
  "iconUrl": "https://media.forgecdn.net/avatars/107/320/636365110095052461.png",
  "iconCid": "bafkreiahgbp4oiqzom7mzpj3zmhjp464moy6s6s3z3pl5jx7sbhnzgixqm",
  "numberOfDownloads": 219,
  "releasesPageUrl": "https://dev.bukkit.org/projects/consolecmd/files",
  "releaseDate": 1500932209000,
  "updateDate": 1500932358000
}