{
  "id": 374457,
  "url": "https://dev.bukkit.org/projects/simplestaff-chat",
  "name": "StaffChat+",
  "description": "Lightweight, easy and configurable staff chat",
  "archived": true,
  "authors": [
    "Forge_User_44441245"
  ],
  "iconUrl": "https://media.forgecdn.net/avatars/262/239/637220253575545872.png",
  "iconCid": "bafkreihpz2pnmjt7gkkcoqsh27yihr7fhwd262ehaxiibivuur25j3sdvi",
  "numberOfDownloads": 489,
  "releasesPageUrl": "https://dev.bukkit.org/projects/simplestaff-chat/files",
  "releaseDate": 1586428557000,
  "updateDate": 1586428862000
}