{
  "id": 293657,
  "url": "https://dev.bukkit.org/projects/playerstalker",
  "name": "PlayerStalker",
  "description": "PlayerStalker",
  "archived": true,
  "authors": [
    "Forge_User_08244060"
  ],
  "iconUrl": "https://media.forgecdn.net/avatars/152/985/636615456135907362.png",
  "iconCid": "bafkreibytagyhp4go6ycx6p2mlqrbb23k4ztky2bm26a5erpdukoxn3vuq",
  "numberOfDownloads": 204,
  "releasesPageUrl": "https://dev.bukkit.org/projects/playerstalker/files",
  "gitUrl": "https://github.com/DanielTheJavaDeveloper/PlayerStalker",
  "releaseDate": 1525948813000,
  "updateDate": 1525949210000
}