{
  "id": 279885,
  "url": "https://dev.bukkit.org/projects/broadcast-command",
  "name": "Broadcast Command",
  "description": "Use /broadcast to broadcast a message or let the auto-broadcaster do the work for you!",
  "archived": true,
  "authors": [
    "Forge_User_31843757"
  ],
  "iconUrl": "https://media.forgecdn.net/avatars/126/952/636434866925590868.png",
  "iconCid": "bafkreia4anaez7vajgfegi6fipbtwbsjf7afkfk4bzco7x2wcfbnq4vi7i",
  "numberOfDownloads": 3,
  "releasesPageUrl": "https://dev.bukkit.org/projects/broadcast-command/files",
  "releaseDate": 1507907745000,
  "updateDate": 1510078060000
}