{
  "id": 320877,
  "url": "https://dev.bukkit.org/projects/singlepersonsleep",
  "name": "SinglePersonSleep",
  "description": "Another plugin for single player sleeping. ",
  "archived": false,
  "authors": [
    "alantr7"
  ],
  "iconUrl": "https://media.forgecdn.net/avatars/202/358/636925952133650581.png",
  "iconCid": "bafkreifr7ien7a7xhhdffvhq6qn3e2554jjvy6exqlpb4resz6digolpyu",
  "numberOfDownloads": 13,
  "releasesPageUrl": "https://dev.bukkit.org/projects/singlepersonsleep/files",
  "releaseDate": 1556998413000,
  "updateDate": 1579992640000
}