{
  "id": 402624,
  "url": "https://dev.bukkit.org/projects/controledejogo",
  "name": "ControleDeJogo",
  "description": "Um Controlador para Minecraft que visa deixar a experiência, em servidores survivals em multiplayers mais imersiva.",
  "archived": false,
  "authors": [
    "FelipeAlafy"
  ],
  "iconUrl": "https://media.forgecdn.net/avatars/294/55/637331823009321246.png",
  "iconCid": "bafkreihwqgksyldlihxmvvyy7ptndv4i4y7nwbt5bvhihkwcew2eqyfos4",
  "numberOfDownloads": 80,
  "releasesPageUrl": "https://dev.bukkit.org/projects/controledejogo/files",
  "releaseDate": 1597585500000,
  "updateDate": 1598141507000
}