{
  "id": 289428,
  "url": "https://dev.bukkit.org/projects/mythicmobsextension",
  "name": "MythicMobsExtension",
  "description": "Useful additions to MythicMobs",
  "archived": true,
  "authors": [
    "Forge_User_95217171"
  ],
  "iconUrl": "https://media.forgecdn.net/avatars/144/612/636557058559478984.png",
  "iconCid": "bafkreibl23orj6ckmelqgq3koo4z2c7teysyxkdya75kvwybks55guy55q",
  "numberOfDownloads": 955,
  "releasesPageUrl": "https://dev.bukkit.org/projects/mythicmobsextension/files",
  "releaseDate": 1520109055000,
  "updateDate": 1544219634000
}