{
  "id": 103502,
  "url": "https://www.spigotmc.org/resources/discordwebhookplugin.103502/",
  "name": "DiscordWebhookPlugin",
  "description": "With this plugin can you send Discord Messages from Minecraft or Join/Leave messages.",
  "authors": [
    "CODEALI"
  ],
  "iconUrl": "https://www.spigotmc.org/data/resource_icons/103/103502.jpg?1658428888",
  "iconCid": "bafkreigvxio7huce353ro7jzkx5cfy2gowyq3eodh6tiezhz2zn4xrj3em",
  "numberOfDownloads": 280,
  "rating": 5,
  "numberOfVotes": 2,
  "releasesPageUrl": "https://www.spigotmc.org/resources/discordwebhookplugin.103502/history",
  "gitUrl": "https://github.com/Ali-Faruk/SpigotMC/tree/main/DiscordWebhookPlugin",
  "releaseDate": 1658241480000,
  "updateDate": 1660588800000,
  "versions": [
    "1.7",
    "1.8",
    "1.9",
    "1.10",
    "1.11",
    "1.12",
    "1.13",
    "1.14",
    "1.15",
    "1.16",
    "1.17",
    "1.18",
    "1.19"
  ]
}