{
  "id": 68006,
  "url": "https://dev.bukkit.org/projects/brewery",
  "name": "Brewery",
  "description": "Brew alcoholic potions, get drunk and have fun!",
  "archived": false,
  "authors": [
    "Sn0wyStorm",
    "GrafePZL"
  ],
  "iconUrl": "https://media.forgecdn.net/avatars/71/999/636163326300129731.jpg",
  "iconCid": "bafkreig2vc2liwhllyzacirxdumjbxcozdi55k6tghgikpfexlka7rbhfa",
  "numberOfDownloads": 96,
  "releasesPageUrl": "https://dev.bukkit.org/projects/brewery/files",
  "gitUrl": "https://github.com/DieReicheErethons/Brewery",
  "releaseDate": 1382818912000,
  "updateDate": 1657470452000
}