{
  "id": 372279,
  "url": "https://dev.bukkit.org/projects/customessentials",
  "name": "CustomEssentials",
  "description": "The fully customizable essentials.",
  "archived": true,
  "authors": [
    "Forge_User_80692148"
  ],
  "iconUrl": "https://media.forgecdn.net/avatars/259/818/637212617286756788.jpeg",
  "iconCid": "bafkreiaie42fqrt72xj2dkxmn5k4ge2pu5mabg4q5jsv6fiuje7hgdu4ku",
  "numberOfDownloads": 559,
  "releasesPageUrl": "https://dev.bukkit.org/projects/customessentials/files",
  "gitUrl": "https://github.com/adamo45/customessentials",
  "releaseDate": 1585664928000,
  "updateDate": 1585854246000
}