{
  "id": 107395,
  "url": "https://www.spigotmc.org/resources/findmyhorse-find-your-own-horses.107395/",
  "name": "FindMyHorse | find your own horses",
  "description": "Simple plugin that finds the coordinates of your horses.",
  "authors": [
    "HeySiri"
  ],
  "numberOfDownloads": 13,
  "rating": 0,
  "numberOfVotes": 0,
  "releasesPageUrl": "https://www.spigotmc.org/resources/findmyhorse-find-your-own-horses.107395/history",
  "gitUrl": "https://github.com/HiBixby/FindMyHorse",
  "releaseDate": 1673771220000,
  "updateDate": 1673771220000,
  "versions": [
    "1.19"
  ]
}