{
  "id": 91849,
  "url": "https://dev.bukkit.org/projects/webop-reborn",
  "name": "WebOp Reborn",
  "description": "WebOp Reborn",
  "archived": false,
  "authors": [
    "FabioZumbi12"
  ],
  "iconUrl": "https://media.forgecdn.net/avatars/275/580/637262725596179563.png",
  "iconCid": "bafkreiaexj2ccja5uhtl4xcr2e7t5j2sxkc7je7gzrvzmy4nhvk4erumhy",
  "numberOfDownloads": 1,
  "releasesPageUrl": "https://dev.bukkit.org/projects/webop-reborn/files",
  "gitUrl": "https://github.com/FabioZumbi12/WebOp",
  "releaseDate": 1431366431000,
  "updateDate": 1592115974000
}