{
  "id": 67724,
  "url": "https://www.spigotmc.org/resources/horse-armor-crafter.67724/",
  "name": "Horse Armor Crafter",
  "description": "Craft the armour and sadels you have always wanted",
  "authors": [
    "jaimyjackson"
  ],
  "numberOfDownloads": 5478,
  "rating": 5,
  "numberOfVotes": 1,
  "releasesPageUrl": "https://www.spigotmc.org/resources/horse-armor-crafter.67724/history",
  "releaseDate": 1558872600000,
  "updateDate": 1655737980000,
  "versions": [
    "1.14",
    "1.15",
    "1.16",
    "1.17",
    "1.18",
    "1.19"
  ]
}