{
  "id": 554203,
  "url": "https://dev.bukkit.org/projects/trample-disabler",
  "name": "Trample Disabler",
  "description": "Disable trampling for all entities",
  "archived": false,
  "authors": [
    "gnappoforever"
  ],
  "iconUrl": "https://media.forgecdn.net/avatars/464/771/637744815587442480.jpeg",
  "iconCid": "bafkreie7q24rl52yl2f34gxshgblylkp2hh55fakww7rkp7x5u3k5tieju",
  "numberOfDownloads": 36,
  "releasesPageUrl": "https://dev.bukkit.org/projects/trample-disabler/files",
  "gitUrl": "https://github.com/gnappoforever/trample-disabler",
  "releaseDate": 1638884758000,
  "updateDate": 1675693937000
}