{
  "id": 698314,
  "url": "https://dev.bukkit.org/projects/batistes-wireless-redstone",
  "name": "Batiste's Wireless Redstone",
  "description": "Wireless redstone without commands or storage of any kind",
  "archived": false,
  "authors": [
    "SirBatiste"
  ],
  "iconUrl": "https://media.forgecdn.net/avatars/632/893/638033523086739255.png",
  "iconCid": "bafkreic6xaqsmrzxnn6a5lohmmvut6zcgzxorywx3e6q3wrxvq6rbqxcda",
  "numberOfDownloads": 161,
  "releasesPageUrl": "https://dev.bukkit.org/projects/batistes-wireless-redstone/files",
  "releaseDate": 1667755508000,
  "updateDate": 1667925312000
}