{
  "id": 107942,
  "url": "https://www.spigotmc.org/resources/blockremover.107942/",
  "name": "BlockRemover",
  "description": "BlockRemover 1.0v",
  "authors": [
    "DO1TA"
  ],
  "iconUrl": "https://www.spigotmc.org/data/resource_icons/107/107942.jpg?1676096288",
  "iconCid": "bafkreih3nmpg6r5he3di3c4k7nhxdribuqqxoq5vcghnj3xdjkpn63ffrm",
  "numberOfDownloads": 11,
  "rating": 5,
  "numberOfVotes": 1,
  "releasesPageUrl": "https://www.spigotmc.org/resources/blockremover.107942/history",
  "releaseDate": 1676092620000,
  "updateDate": 1676092620000,
  "versions": []
}