{
  "id": 99506,
  "url": "https://www.spigotmc.org/resources/%E2%98%81%EF%B8%8E-epiclobbyutils-%E2%98%85-1-8-1-18-support.99506/",
  "name": "☁︎ EpicLobbyUtils ★ 1.8 - 1.18 support",
  "description": "A plugin that provides social network commands and utilities for your lobby!",
  "authors": [
    "GabrielB82"
  ],
  "iconUrl": "https://www.spigotmc.org/data/resource_icons/99/99506.jpg?1643119853",
  "iconCid": "bafkreica4x4vaohtsrlqrk5bcsintvmygtcgrdnpsdotvhctjxm2dwo7iy",
  "numberOfDownloads": 45,
  "rating": 0,
  "numberOfVotes": 0,
  "releasesPageUrl": "https://www.spigotmc.org/resources/%E2%98%81%EF%B8%8E-epiclobbyutils-%E2%98%85-1-8-1-18-support.99506/history",
  "releaseDate": 1643116200000,
  "updateDate": 1643116200000,
  "versions": [
    "1.8",
    "1.9",
    "1.10",
    "1.11",
    "1.12",
    "1.13",
    "1.14",
    "1.15",
    "1.16",
    "1.17",
    "1.18"
  ]
}