{
  "id": 42857,
  "url": "https://dev.bukkit.org/projects/harrypotterspells",
  "name": "HarryPotterSpells",
  "description": "The complete Harry Potter plugin!  From the Killing Curse to the Sorting Hat, HarryPotterSpells has it all!",
  "archived": false,
  "authors": [
    "Jacklin213",
    "_ForgeUser10954152",
    "_ForgeUser12168821",
    "Forge_User_27973310",
    "Forge_User_54939262",
    "Forge_User_59704745",
    "Forge_User_92930383",
    "nikgenic",
    "SpiralDown"
  ],
  "iconUrl": "https://media.forgecdn.net/avatars/74/784/636164207953509119.jpg",
  "iconCid": "bafybeidqklb6gxytsvuoas3day26modvckaxlrurkim7jewxyyufcm5zna",
  "numberOfDownloads": 58,
  "releasesPageUrl": "https://dev.bukkit.org/projects/harrypotterspells/files",
  "gitUrl": "https://github.com/HarryPotterSpells/HarryPotterSpells",
  "releaseDate": 1344108394000,
  "updateDate": 1586969994000
}